README
setup.py
smoke.py
smoke.egg-info/PKG-INFO
smoke.egg-info/SOURCES.txt
smoke.egg-info/dependency_links.txt
smoke.egg-info/requires.txt
smoke.egg-info/top_level.txt