Metadata-Version: 1.0
Name: smoke
Version: 0.2.0
Summary: concise publish/subscribe utility
Home-page: UNKNOWN
Author: David Keijser
Author-email: keijser@gmail.com
License: MIT
Keywords: publish subscribe pubsub signal
Platform: UNKNOWN
